{
  "data": [
    {
      "ip": "192.168.9.81",
      "mac": "FC:52:CE:87:B0:17",
      "serial": "00014003750271572",
      "firmware": 1048,
      "mrp": 1560,
      "memoriaUtilizada": 18,
      "ultimoNroNSR": 159959,
      "totalUsuarios": 749,
      "usuarios": 749,
      "usuariosAdmin": 19,
      "digitaisCadastradas": 614,
      "usuariosComSenha": 12,
      "codigoBarras": 0,
      "cartoesRfid": 0,
      "tempoAtividade": "0d 5h 8m 51s",
      "totalTicketsImpressos": 158630,
      "qtdBobina": 0,
      "totalBobina": 79213,
      "prontoImpressao": true,
      "acabandoBobina": false,
      "lastSyncDate": "2025-01-23T09:10:05",
      "status": "success"
    },
    {
      "ip": "192.168.9.80",
      "mac": "FC:52:CE:87:B0:A7",
      "serial": "00014003750269196",
      "firmware": 1048,
      "mrp": 1560,
      "memoriaUtilizada": 20,
      "ultimoNroNSR": 342251,
      "totalUsuarios": 759,
      "usuarios": 759,
      "usuariosAdmin": 23,
      "digitaisCadastradas": 746,
      "usuariosComSenha": 12,
      "codigoBarras": 0,
      "cartoesRfid": 0,
      "tempoAtividade": "0d 5h 15m 9s",
      "totalTicketsImpressos": 341646,
      "qtdBobina": 0,
      "totalBobina": 230562,
      "prontoImpressao": true,
      "acabandoBobina": false,
      "lastSyncDate": "2025-01-23T09:10:05",
      "status": "success"
    },
    {
      "ip": "192.168.3.81",
      "mac": "FC:52:CE:83:70:DA",
      "serial": "00014003750136782",
      "firmware": 1048,
      "mrp": 1560,
      "memoriaUtilizada": 21,
      "ultimoNroNSR": 506981,
      "totalUsuarios": 830,
      "usuarios": 830,
      "usuariosAdmin": 7,
      "digitaisCadastradas": 400,
      "usuariosComSenha": 57,
      "codigoBarras": 0,
      "cartoesRfid": 2,
      "tempoAtividade": "0d 10h 23m 41s",
      "totalTicketsImpressos": 501530,
      "qtdBobina": 0,
      "totalBobina": 280144,
      "prontoImpressao": true,
      "acabandoBobina": false,
      "lastSyncDate": "2025-01-23T09:10:05",
      "status": "success"
    },
    {
      "ip": "192.168.13.41",
      "mac": "FC:52:CE:85:6B:DB",
      "serial": "00014003750169746",
      "firmware": 1048,
      "mrp": 1560,
      "memoriaUtilizada": 23,
      "ultimoNroNSR": 299999,
      "totalUsuarios": 1352,
      "usuarios": 1352,
      "usuariosAdmin": 16,
      "digitaisCadastradas": 1765,
      "usuariosComSenha": 13,
      "codigoBarras": 0,
      "cartoesRfid": 2,
      "tempoAtividade": "0d 7h 58m 22s",
      "totalTicketsImpressos": 297621,
      "qtdBobina": 0,
      "totalBobina": 191915,
      "prontoImpressao": true,
      "acabandoBobina": false,
      "lastSyncDate": "2025-01-23T09:10:05",
      "status": "success"
    },
    {
      "ip": "192.168.1.80",
      "mac": "FC:52:CE:81:EB:24",
      "serial": "00014003750062773",
      "firmware": 1048,
      "mrp": 1560,
      "memoriaUtilizada": 27,
      "ultimoNroNSR": 1029566,
      "totalUsuarios": 2621,
      "usuarios": 2621,
      "usuariosAdmin": 8,
      "digitaisCadastradas": 2574,
      "usuariosComSenha": 65,
      "codigoBarras": 0,
      "cartoesRfid": 2,
      "tempoAtividade": "0d 12h 57m 58s",
      "totalTicketsImpressos": 1021153,
      "qtdBobina": 0,
      "totalBobina": 621890,
      "prontoImpressao": true,
      "acabandoBobina": false,
      "lastSyncDate": "2025-01-23T09:10:05",
      "status": "success"
    },
    {
      "ip": "172.98.2.81",
      "mac": "FC:52:CE:87:91:79",
      "serial": "00014003750253545",
      "firmware": 1048,
      "mrp": 1560,
      "memoriaUtilizada": 18,
      "ultimoNroNSR": 91541,
      "totalUsuarios": 424,
      "usuarios": 424,
      "usuariosAdmin": 6,
      "digitaisCadastradas": 479,
      "usuariosComSenha": 9,
      "codigoBarras": 0,
      "cartoesRfid": 0,
      "tempoAtividade": "0d 3h 50m 6s",
      "totalTicketsImpressos": 90736,
      "qtdBobina": 0,
      "totalBobina": 61446,
      "prontoImpressao": true,
      "acabandoBobina": false,
      "lastSyncDate": "2025-01-23T09:10:05",
      "status": "success"
    },
    {
      "ip": "192.168.6.81",
      "mac": "FC:52:CE:84:42:3F",
      "serial": "00014003750160329",
      "firmware": 1048,
      "mrp": 1560,
      "memoriaUtilizada": 25,
      "ultimoNroNSR": 619254,
      "totalUsuarios": 2518,
      "usuarios": 2518,
      "usuariosAdmin": 22,
      "digitaisCadastradas": 2048,
      "usuariosComSenha": 11,
      "codigoBarras": 0,
      "cartoesRfid": 2,
      "tempoAtividade": "0d 8h 54m 40s",
      "totalTicketsImpressos": 614095,
      "qtdBobina": 0,
      "totalBobina": 305081,
      "prontoImpressao": true,
      "acabandoBobina": false,
      "lastSyncDate": "2025-01-23T09:10:05",
      "status": "success"
    },
    {
      "ip": "192.168.6.82",
      "mac": "FC:52:CE:84:54:FE",
      "serial": "00014003750159245",
      "firmware": 1048,
      "mrp": 1560,
      "memoriaUtilizada": 24,
      "ultimoNroNSR": 640929,
      "totalUsuarios": 2386,
      "usuarios": 2386,
      "usuariosAdmin": 20,
      "digitaisCadastradas": 1690,
      "usuariosComSenha": 10,
      "codigoBarras": 0,
      "cartoesRfid": 1,
      "tempoAtividade": "0d 8h 59m 17s",
      "totalTicketsImpressos": 640120,
      "qtdBobina": 0,
      "totalBobina": 318073,
      "prontoImpressao": true,
      "acabandoBobina": false,
      "lastSyncDate": "2025-01-23T09:10:05",
      "status": "success"
    },
    {
      "ip": "172.98.2.80",
      "mac": "FC:52:CE:87:92:3B",
      "serial": "00014003750219361",
      "firmware": 1048,
      "mrp": 1560,
      "memoriaUtilizada": 20,
      "ultimoNroNSR": 171287,
      "totalUsuarios": 757,
      "usuarios": 757,
      "usuariosAdmin": 4,
      "digitaisCadastradas": 942,
      "usuariosComSenha": 9,
      "codigoBarras": 0,
      "cartoesRfid": 1,
      "tempoAtividade": "0d 4h 16m 22s",
      "totalTicketsImpressos": 169746,
      "qtdBobina": 0,
      "totalBobina": 114116,
      "prontoImpressao": true,
      "acabandoBobina": false,
      "lastSyncDate": "2025-01-23T09:10:05",
      "status": "success"
    },
    {
      "ip": "192.168.17.81",
      "mac": "FC:52:CE:86:BA:C0",
      "serial": "00014003750215890",
      "firmware": 1048,
      "mrp": 1560,
      "memoriaUtilizada": 21,
      "ultimoNroNSR": 332763,
      "totalUsuarios": 1370,
      "usuarios": 1370,
      "usuariosAdmin": 14,
      "digitaisCadastradas": 1221,
      "usuariosComSenha": 5,
      "codigoBarras": 0,
      "cartoesRfid": 2,
      "tempoAtividade": "0d 5h 44m 28s",
      "totalTicketsImpressos": 333571,
      "qtdBobina": 0,
      "totalBobina": 166322,
      "prontoImpressao": true,
      "acabandoBobina": false,
      "lastSyncDate": "2025-01-23T09:10:05",
      "status": "success"
    },
    {
      "ip": "10.10.1.82",
      "mac": "FC:52:CE:83:ED:4E",
      "serial": "00014003750108408",
      "firmware": 1048,
      "mrp": 1560,
      "memoriaUtilizada": 19,
      "ultimoNroNSR": 55260,
      "totalUsuarios": 552,
      "usuarios": 552,
      "usuariosAdmin": 7,
      "digitaisCadastradas": 674,
      "usuariosComSenha": 11,
      "codigoBarras": 0,
      "cartoesRfid": 1,
      "tempoAtividade": "0d 9h 51m 22s",
      "totalTicketsImpressos": 54474,
      "qtdBobina": 0,
      "totalBobina": 38196,
      "prontoImpressao": true,
      "acabandoBobina": false,
      "lastSyncDate": "2025-01-23T09:10:05",
      "status": "success"
    },
    {
      "ip": "192.168.4.81",
      "mac": "FC:52:CE:83:B4:5E",
      "serial": "00014003750140275",
      "firmware": 1048,
      "mrp": 1560,
      "memoriaUtilizada": 25,
      "ultimoNroNSR": 375277,
      "totalUsuarios": 1122,
      "usuarios": 1122,
      "usuariosAdmin": 16,
      "digitaisCadastradas": 1989,
      "usuariosComSenha": 37,
      "codigoBarras": 0,
      "cartoesRfid": 2,
      "tempoAtividade": "0d 9h 36m 15s",
      "totalTicketsImpressos": 375292,
      "qtdBobina": 0,
      "totalBobina": 214209,
      "prontoImpressao": true,
      "acabandoBobina": false,
      "lastSyncDate": "2025-01-23T09:10:05",
      "status": "success"
    },
    {
      "ip": "192.168.26.80",
      "mac": "FC:52:CE:89:94:89",
      "serial": "00014003750222950",
      "firmware": 257,
      "mrp": 256,
      "memoriaUtilizada": 27,
      "ultimoNroNSR": 257899,
      "totalUsuarios": 1827,
      "usuarios": 1827,
      "usuariosAdmin": 3,
      "digitaisCadastradas": 1956,
      "usuariosComSenha": 9,
      "codigoBarras": 0,
      "cartoesRfid": 1,
      "tempoAtividade": "0d 3h 0m 27s",
      "totalTicketsImpressos": 254044,
      "qtdBobina": 0,
      "totalBobina": 162683,
      "prontoImpressao": true,
      "acabandoBobina": false,
      "lastSyncDate": "2025-01-23T09:10:05",
      "status": "success"
    },
    {
      "ip": "10.10.1.81",
      "mac": "FC:52:CE:85:9C:92",
      "serial": "00014003750174671",
      "firmware": 1048,
      "mrp": 1560,
      "memoriaUtilizada": 19,
      "ultimoNroNSR": 67414,
      "totalUsuarios": 548,
      "usuarios": 548,
      "usuariosAdmin": 7,
      "digitaisCadastradas": 653,
      "usuariosComSenha": 11,
      "codigoBarras": 1,
      "cartoesRfid": 2,
      "tempoAtividade": "0d 7h 27m 9s",
      "totalTicketsImpressos": 66401,
      "qtdBobina": 0,
      "totalBobina": 45043,
      "prontoImpressao": true,
      "acabandoBobina": false,
      "lastSyncDate": "2025-01-23T09:10:06",
      "status": "success"
    },
    {
      "ip": "192.168.21.80",
      "mac": "FC:52:CE:88:18:8F",
      "serial": "00014003750250078",
      "firmware": 1048,
      "mrp": 1560,
      "memoriaUtilizada": 19,
      "ultimoNroNSR": 326494,
      "totalUsuarios": 638,
      "usuarios": 638,
      "usuariosAdmin": 12,
      "digitaisCadastradas": 735,
      "usuariosComSenha": 13,
      "codigoBarras": 0,
      "cartoesRfid": 1,
      "tempoAtividade": "0d 4h 43m 31s",
      "totalTicketsImpressos": 325645,
      "qtdBobina": 0,
      "totalBobina": 219973,
      "prontoImpressao": true,
      "acabandoBobina": false,
      "lastSyncDate": "2025-01-23T09:10:06",
      "status": "success"
    },
    {
      "ip": "192.168.18.81",
      "mac": "FC:52:CE:88:2D:2D",
      "serial": "00014003750242190",
      "firmware": 1048,
      "mrp": 1560,
      "memoriaUtilizada": 35,
      "ultimoNroNSR": 249425,
      "totalUsuarios": 3703,
      "usuarios": 3703,
      "usuariosAdmin": 14,
      "digitaisCadastradas": 3707,
      "usuariosComSenha": 23,
      "codigoBarras": 0,
      "cartoesRfid": 1,
      "tempoAtividade": "0d 4h 21m 50s",
      "totalTicketsImpressos": 242668,
      "qtdBobina": 0,
      "totalBobina": 155915,
      "prontoImpressao": true,
      "acabandoBobina": false,
      "lastSyncDate": "2025-01-23T09:10:06",
      "status": "success"
    },
    {
      "ip": "192.168.19.82",
      "mac": "FC:52:CE:86:AA:86",
      "serial": "00014003750214147",
      "firmware": 1048,
      "mrp": 1560,
      "memoriaUtilizada": 19,
      "ultimoNroNSR": 154158,
      "totalUsuarios": 777,
      "usuarios": 777,
      "usuariosAdmin": 13,
      "digitaisCadastradas": 814,
      "usuariosComSenha": 11,
      "codigoBarras": 0,
      "cartoesRfid": 2,
      "tempoAtividade": "0d 5h 30m 53s",
      "totalTicketsImpressos": 150981,
      "qtdBobina": 0,
      "totalBobina": 77008,
      "prontoImpressao": true,
      "acabandoBobina": false,
      "lastSyncDate": "2025-01-23T09:10:06",
      "status": "success"
    },
    {
      "ip": "10.10.1.80",
      "mac": "FC:52:CE:82:0B:A1",
      "serial": "00014003750091132",
      "firmware": 1048,
      "mrp": 1560,
      "memoriaUtilizada": 18,
      "ultimoNroNSR": 137841,
      "totalUsuarios": 353,
      "usuarios": 353,
      "usuariosAdmin": 8,
      "digitaisCadastradas": 522,
      "usuariosComSenha": 9,
      "codigoBarras": 0,
      "cartoesRfid": 1,
      "tempoAtividade": "0d 12h 22m 36s",
      "totalTicketsImpressos": 135912,
      "qtdBobina": 0,
      "totalBobina": 95490,
      "prontoImpressao": true,
      "acabandoBobina": false,
      "lastSyncDate": "2025-01-23T09:10:06",
      "status": "success"
    },
    {
      "ip": "192.168.3.80",
      "mac": "FC:52:CE:83:C6:CF",
      "serial": "00014003750140652",
      "firmware": 1048,
      "mrp": 1560,
      "memoriaUtilizada": 19,
      "ultimoNroNSR": 386685,
      "totalUsuarios": 1002,
      "usuarios": 1002,
      "usuariosAdmin": 7,
      "digitaisCadastradas": 422,
      "usuariosComSenha": 78,
      "codigoBarras": 0,
      "cartoesRfid": 3,
      "tempoAtividade": "0d 8h 8m 41s",
      "totalTicketsImpressos": 384525,
      "qtdBobina": 0,
      "totalBobina": 203805,
      "prontoImpressao": true,
      "acabandoBobina": false,
      "lastSyncDate": "2025-01-23T09:10:06",
      "status": "success"
    },
    {
      "ip": "192.168.7.81",
      "mac": "FC:52:CE:84:E0:9C",
      "serial": "00014003750152780",
      "firmware": 1048,
      "mrp": 1560,
      "memoriaUtilizada": 22,
      "ultimoNroNSR": 542330,
      "totalUsuarios": 1620,
      "usuarios": 1620,
      "usuariosAdmin": 16,
      "digitaisCadastradas": 1533,
      "usuariosComSenha": 11,
      "codigoBarras": 0,
      "cartoesRfid": 2,
      "tempoAtividade": "0d 8h 22m 5s",
      "totalTicketsImpressos": 540835,
      "qtdBobina": 0,
      "totalBobina": 311273,
      "prontoImpressao": true,
      "acabandoBobina": false,
      "lastSyncDate": "2025-01-23T09:10:06",
      "status": "success"
    },
    {
      "ip": "192.168.12.40",
      "mac": "FC:52:CE:85:0E:13",
      "serial": "00014003750177316",
      "firmware": 1048,
      "mrp": 1560,
      "memoriaUtilizada": 26,
      "ultimoNroNSR": 303110,
      "totalUsuarios": 2473,
      "usuarios": 2473,
      "usuariosAdmin": 19,
      "digitaisCadastradas": 2481,
      "usuariosComSenha": 70,
      "codigoBarras": 0,
      "cartoesRfid": 1,
      "tempoAtividade": "0d 7h 42m 7s",
      "totalTicketsImpressos": 299163,
      "qtdBobina": 0,
      "totalBobina": 148564,
      "prontoImpressao": true,
      "acabandoBobina": false,
      "lastSyncDate": "2025-01-23T09:10:06",
      "status": "success"
    },
    {
      "ip": "172.98.2.82",
      "mac": "FC:52:CE:85:0C:CA",
      "serial": "00014003750180703",
      "firmware": 1048,
      "mrp": 1560,
      "memoriaUtilizada": 20,
      "ultimoNroNSR": 522970,
      "totalUsuarios": 932,
      "usuarios": 932,
      "usuariosAdmin": 7,
      "digitaisCadastradas": 1068,
      "usuariosComSenha": 8,
      "codigoBarras": 0,
      "cartoesRfid": 1,
      "tempoAtividade": "0d 8h 12m 43s",
      "totalTicketsImpressos": 518466,
      "qtdBobina": 0,
      "totalBobina": 337462,
      "prontoImpressao": true,
      "acabandoBobina": false,
      "lastSyncDate": "2025-01-23T09:10:06",
      "status": "success"
    },
    {
      "ip": "192.168.21.81",
      "mac": "FC:52:CE:88:18:9F",
      "serial": "00014003750250657",
      "firmware": 1048,
      "mrp": 1560,
      "memoriaUtilizada": 18,
      "ultimoNroNSR": 80496,
      "totalUsuarios": 583,
      "usuarios": 583,
      "usuariosAdmin": 9,
      "digitaisCadastradas": 654,
      "usuariosComSenha": 10,
      "codigoBarras": 0,
      "cartoesRfid": 1,
      "tempoAtividade": "0d 4h 36m 59s",
      "totalTicketsImpressos": 79813,
      "qtdBobina": 0,
      "totalBobina": 52463,
      "prontoImpressao": true,
      "acabandoBobina": false,
      "lastSyncDate": "2025-01-23T09:10:06",
      "status": "success"
    },
    {
      "ip": "192.168.10.81",
      "mac": "FC:52:CE:86:16:CB",
      "serial": "00014003750210277",
      "firmware": 1048,
      "mrp": 1560,
      "memoriaUtilizada": 20,
      "ultimoNroNSR": 423943,
      "totalUsuarios": 854,
      "usuarios": 854,
      "usuariosAdmin": 18,
      "digitaisCadastradas": 952,
      "usuariosComSenha": 13,
      "codigoBarras": 0,
      "cartoesRfid": 2,
      "tempoAtividade": "0d 6h 24m 40s",
      "totalTicketsImpressos": 423892,
      "qtdBobina": 0,
      "totalBobina": 207021,
      "prontoImpressao": true,
      "acabandoBobina": false,
      "lastSyncDate": "2025-01-23T09:10:06",
      "status": "success"
    },
    {
      "ip": "192.168.11.83",
      "mac": "FC:52:CE:85:0C:82",
      "serial": "00014003750180769",
      "firmware": 1048,
      "mrp": 1560,
      "memoriaUtilizada": 23,
      "ultimoNroNSR": 480528,
      "totalUsuarios": 1451,
      "usuarios": 1451,
      "usuariosAdmin": 20,
      "digitaisCadastradas": 1275,
      "usuariosComSenha": 41,
      "codigoBarras": 0,
      "cartoesRfid": 1,
      "tempoAtividade": "0d 8h 12m 14s",
      "totalTicketsImpressos": 480534,
      "qtdBobina": 0,
      "totalBobina": 324354,
      "prontoImpressao": true,
      "acabandoBobina": false,
      "lastSyncDate": "2025-01-23T09:10:06",
      "status": "success"
    },
    {
      "ip": "192.168.11.82",
      "mac": "FC:52:CE:85:0E:22",
      "serial": "00014003750181342",
      "firmware": 1048,
      "mrp": 1560,
      "memoriaUtilizada": 20,
      "ultimoNroNSR": 412974,
      "totalUsuarios": 1119,
      "usuarios": 1119,
      "usuariosAdmin": 18,
      "digitaisCadastradas": 1090,
      "usuariosComSenha": 38,
      "codigoBarras": 1,
      "cartoesRfid": 2,
      "tempoAtividade": "0d 8h 6m 39s",
      "totalTicketsImpressos": 419387,
      "qtdBobina": 0,
      "totalBobina": 281385,
      "prontoImpressao": true,
      "acabandoBobina": false,
      "lastSyncDate": "2025-01-23T09:10:06",
      "status": "success"
    },
    {
      "ip": "192.168.5.80",
      "mac": "FC:52:CE:83:EB:E2",
      "serial": "00014003750119565",
      "firmware": 1048,
      "mrp": 1560,
      "memoriaUtilizada": 27,
      "ultimoNroNSR": 510224,
      "totalUsuarios": 2088,
      "usuarios": 2088,
      "usuariosAdmin": 27,
      "digitaisCadastradas": 2378,
      "usuariosComSenha": 7,
      "codigoBarras": 0,
      "cartoesRfid": 2,
      "tempoAtividade": "0d 10h 3m 41s",
      "totalTicketsImpressos": 502877,
      "qtdBobina": 0,
      "totalBobina": 306720,
      "prontoImpressao": true,
      "acabandoBobina": false,
      "lastSyncDate": "2025-01-23T09:10:06",
      "status": "success"
    },
    {
      "ip": "192.168.23.81",
      "mac": "FC:52:CE:89:05:7D",
      "serial": "00014003750235552",
      "firmware": 257,
      "mrp": 256,
      "memoriaUtilizada": 17,
      "ultimoNroNSR": 76331,
      "totalUsuarios": 605,
      "usuarios": 605,
      "usuariosAdmin": 3,
      "digitaisCadastradas": 291,
      "usuariosComSenha": 4,
      "codigoBarras": 0,
      "cartoesRfid": 0,
      "tempoAtividade": "0d 4h 7m 9s",
      "totalTicketsImpressos": 75386,
      "qtdBobina": 0,
      "totalBobina": 51106,
      "prontoImpressao": true,
      "acabandoBobina": false,
      "lastSyncDate": "2025-01-23T09:10:06",
      "status": "success"
    },
    {
      "ip": "192.168.7.80",
      "mac": "FC:52:CE:84:DE:9B",
      "serial": "00014003750152916",
      "firmware": 1048,
      "mrp": 1560,
      "memoriaUtilizada": 21,
      "ultimoNroNSR": 325426,
      "totalUsuarios": 1559,
      "usuarios": 1559,
      "usuariosAdmin": 19,
      "digitaisCadastradas": 1204,
      "usuariosComSenha": 11,
      "codigoBarras": 0,
      "cartoesRfid": 2,
      "tempoAtividade": "0d 8h 21m 16s",
      "totalTicketsImpressos": 322999,
      "qtdBobina": 0,
      "totalBobina": 185922,
      "prontoImpressao": true,
      "acabandoBobina": false,
      "lastSyncDate": "2025-01-23T09:10:07",
      "status": "success"
    },
    {
      "ip": "192.168.4.80",
      "mac": "FC:52:CE:83:B4:9A",
      "serial": "00014003750139064",
      "firmware": 1048,
      "mrp": 1560,
      "memoriaUtilizada": 24,
      "ultimoNroNSR": 687043,
      "totalUsuarios": 1123,
      "usuarios": 1123,
      "usuariosAdmin": 17,
      "digitaisCadastradas": 2070,
      "usuariosComSenha": 37,
      "codigoBarras": 0,
      "cartoesRfid": 2,
      "tempoAtividade": "0d 10h 11m 51s",
      "totalTicketsImpressos": 687685,
      "qtdBobina": 0,
      "totalBobina": 393328,
      "prontoImpressao": true,
      "acabandoBobina": false,
      "lastSyncDate": "2025-01-23T09:10:12",
      "status": "success"
    }
  ]
}